{
  "automationSettings": {
    "enableIntelligentSequencing": true,
    "enableHealthChecks": true,
    "enableAutoLogin": true,
    "enableMarketHoursAwareness": true,
    "enablePerformanceMonitoring": true,
    "enableAutoUpdates": false,
    "enableCrashPrediction": true,
    "enableResourceOptimization": true,
    "runAsWindowsService": false,
    "emergencyShutdownEnabled": true
  },
  "marketSettings": {
    "primaryTimeZone": "Eastern Standard Time",
    "tradingHours": {
      "monday": {"start": "00:00", "end": "23:59", "enabled": true},
      "tuesday": {"start": "00:00", "end": "23:59", "enabled": true},
      "wednesday": {"start": "00:00", "end": "23:59", "enabled": true},
      "thursday": {"start": "00:00", "end": "23:59", "enabled": true},
      "friday": {"start": "00:00", "end": "22:00", "enabled": true},
      "saturday": {"start": "00:00", "end": "00:00", "enabled": false},
      "sunday": {"start": "17:00", "end": "23:59", "enabled": true}
    },
    "marketHolidays": {
      "description": "Global market holidays by region",
      "usHolidays": [
        "2025-01-01", "2025-01-20", "2025-02-17", "2025-04-18", 
        "2025-05-26", "2025-06-19", "2025-07-04", "2025-09-01", 
        "2025-11-27", "2025-12-25"
      ],
      "ukHolidays": [
        "2025-01-01", "2025-04-18", "2025-04-21", "2025-05-05", 
        "2025-05-26", "2025-08-25", "2025-12-25", "2025-12-26"
      ],
      "japanHolidays": [
        "2025-01-01", "2025-01-13", "2025-02-11", "2025-02-23", 
        "2025-03-20", "2025-04-29", "2025-05-03", "2025-05-04", 
        "2025-05-05", "2025-07-21", "2025-08-11", "2025-09-15", 
        "2025-09-23", "2025-10-13", "2025-11-03", "2025-11-23"
      ],
      "euHolidays": [
        "2025-01-01", "2025-04-18", "2025-04-21", "2025-05-01", 
        "2025-05-29", "2025-08-15", "2025-11-01", "2025-12-25", "2025-12-26"
      ],
      "australiaHolidays": [
        "2025-01-01", "2025-01-27", "2025-04-18", "2025-04-21", 
        "2025-04-25", "2025-06-09", "2025-12-25", "2025-12-26"
      ],
      "globalHolidays": [
        "2025-01-01", "2025-12-25"
      ]
    },
    "marketSessions": {
      "sydney": {
        "start": "17:00", 
        "end": "02:00",
        "timezone": "Australia/Sydney",
        "affectedByHolidays": true,
        "holidayList": "australiaHolidays"
      },
      "tokyo": {
        "start": "19:00", 
        "end": "04:00",
        "timezone": "Asia/Tokyo",
        "affectedByHolidays": true,
        "holidayList": "japanHolidays"
      },
      "london": {
        "start": "03:00", 
        "end": "12:00",
        "timezone": "Europe/London",
        "affectedByHolidays": true,
        "holidayList": "ukHolidays"
      },
      "newYork": {
        "start": "08:00", 
        "end": "17:00",
        "timezone": "America/New_York", 
        "affectedByHolidays": true,
        "holidayList": "usHolidays"
      },
      "frankfurt": {
        "start": "02:00", 
        "end": "11:00",
        "timezone": "Europe/Berlin",
        "affectedByHolidays": true,
        "holidayList": "euHolidays"
      }
    }
  },
  "healthChecks": {
    "connectionTimeout": 30,
    "memoryThresholdWarning": "1.5GB",
    "memoryThresholdCritical": "2.5GB",
    "cpuThresholdWarning": 70,
    "cpuThresholdCritical": 90,
    "checkInterval": 60,
    "healthScoreThreshold": 75,
    "consecutiveFailuresLimit": 3,
    "networkLatencyThreshold": 1000
  },
  "sequencing": {
    "dependencyChain": ["MT4", "MT5", "TraderEvolution"],
    "stabilityWaitTime": 45,
    "maxStartupTime": 300,
    "resourceCheckInterval": 10,
    "minimumSystemMemory": "4GB",
    "minimumDiskSpace": "10GB",
    "networkConnectivityCheck": true
  },
  "performance": {
    "enableAdaptivePriority": true,
    "enableMemoryOptimization": true,
    "enableCpuOptimization": true,
    "monitoringInterval": 30,
    "optimizationInterval": 300,
    "resourceRebalancingEnabled": true,
    "performanceLogging": true
  },
  "recovery": {
    "enablePredictiveMaintenance": true,
    "crashPredictionModel": "statistical",
    "restartStrategies": ["soft", "hard", "cold"],
    "maxRestartAttempts": 5,
    "restartCooldownPeriod": 120,
    "emergencyShutdownThreshold": 95,
    "autoRecoveryEnabled": true,
    "rollbackOnFailure": true
  },
  "security": {
    "encryptCredentials": true,
    "credentialStorage": "WindowsCredentialManager",
    "sessionTokenExpiry": 3600,
    "enableAuditLogging": true,
    "accessControlEnabled": true,
    "secureConnectionsOnly": true
  },
  "logging": {
    "logLevel": "INFO",
    "logRotation": true,
    "maxLogSize": "100MB",
    "logRetentionDays": 30,
    "enableDetailedLogging": true,
    "enablePerformanceMetrics": true,
    "logDirectory": "C:\\Projects\\FinancialData\\Logs\\Advanced"
  },
  "notifications": {
    "enableEmailAlerts": false,
    "enableWindowsNotifications": true,
    "alertOnCriticalErrors": true,
    "alertOnPerformanceIssues": true,
    "alertOnMarketEvents": false,
    "emailSettings": {
      "smtpServer": "",
      "smtpPort": 587,
      "username": "",
      "recipientEmail": ""
    }
  },
  "instances": [
    {
      "name": "AfterPrime_MT4_Demo_Instance",
      "enabled": true,
      "autoStart": true,
      "priority": "normal",
      "startupDelay": 0,
      "dependsOn": [],
      "healthCheckEnabled": true,
      "autoLoginEnabled": false,
      "performanceMonitoring": true,
      "memoryLimit": "1GB",
      "cpuLimit": 25,
      "autoRestart": true,
      "credentialId": "afterprime_mt4_demo",
      "healthThreshold": 80,
      "marketSessionAware": true,
      "allowedSessions": ["london", "newYork"]
    },
    {
      "name": "AfterPrime_MT4_Live_Instance", 
      "enabled": true,
      "autoStart": true,
      "priority": "high",
      "startupDelay": 10,
      "dependsOn": ["AfterPrime_MT4_Demo_Instance"],
      "healthCheckEnabled": true,
      "autoLoginEnabled": true,
      "performanceMonitoring": true,
      "memoryLimit": "1.5GB",
      "cpuLimit": 35,
      "autoRestart": true,
      "credentialId": "afterprime_mt4_live",
      "healthThreshold": 90,
      "marketSessionAware": true,
      "allowedSessions": ["london", "newYork", "tokyo"]
    },
    {
      "name": "AfterPrime_MT5_Live_Instance",
      "enabled": true,
      "autoStart": true,
      "priority": "high",
      "startupDelay": 20,
      "dependsOn": ["AfterPrime_MT4_Live_Instance"],
      "healthCheckEnabled": true,
      "autoLoginEnabled": true,
      "performanceMonitoring": true,
      "memoryLimit": "2GB",
      "cpuLimit": 40,
      "autoRestart": true,
      "credentialId": "afterprime_mt5_live",
      "healthThreshold": 90,
      "marketSessionAware": true,
      "allowedSessions": ["london", "newYork", "tokyo", "sydney"]
    },
    {
      "name": "AfterPrime_TraderEvolution_Live_Instance",
      "enabled": true,
      "autoStart": false,
      "priority": "normal",
      "startupDelay": 30,
      "dependsOn": ["AfterPrime_MT5_Live_Instance"],
      "healthCheckEnabled": true,
      "autoLoginEnabled": false,
      "performanceMonitoring": true,
      "memoryLimit": "1.5GB",
      "cpuLimit": 30,
      "autoRestart": true,
      "credentialId": "afterprime_te_live",
      "healthThreshold": 85,
      "marketSessionAware": true,
      "allowedSessions": ["newYork"]
    },
    {
      "name": "AfterPrime_TraderEvolution_Demo_Instance",
      "enabled": false,
      "autoStart": false,
      "priority": "low",
      "startupDelay": 40,
      "dependsOn": [],
      "healthCheckEnabled": true,
      "autoLoginEnabled": false,
      "performanceMonitoring": false,
      "memoryLimit": "1GB",
      "cpuLimit": 20,
      "autoRestart": false,
      "credentialId": "afterprime_te_demo",
      "healthThreshold": 70,
      "marketSessionAware": false,
      "allowedSessions": []
    }
  ]
}